MANIFEST.in
README.md
recat
setup.json
setup.py
logcatcolor/__init__.py
logcatcolor/column.py
logcatcolor/config.py
logcatcolor/format.py
logcatcolor/layout.py
logcatcolor/mapping.py
logcatcolor/profile.py
logcatcolor/reader.py
logcatcolor/retrace.py
recat_color.egg-info/PKG-INFO
recat_color.egg-info/SOURCES.txt
recat_color.egg-info/dependency_links.txt
recat_color.egg-info/pbr.json
recat_color.egg-info/requires.txt
recat_color.egg-info/top_level.txt
test/test.py