Metadata-Version: 1.0
Name: recat-color
Version: 0.1.1
Summary: A colorful alternative to "adb logcat" with on-the-fly-deobfuscation
Home-page: http://github.com/EverythingMe/recat
Author: Rotem Mizrachi-Meidan
Author-email: rotem@everything.me
License: UNKNOWN
Platform: UNKNOWN
